{
  "entries": [
    {
      "first_name": "Grant",
      "last_name": "Breckenridge",
      "bio": {
        "height": "5'8\"",
        "birthday": "1997-04-08T00:00:00",
        "hometown": {
          "city": "Libertyville",
          "state": "IL",
          "country": "United States",
          "latitude": 42.2814,
          "longitude": -87.9528
        },
        "education": " Stanford University ‘19, Mechanical Engineering ",
        "fun_fact": null,
        "biography": "<h5>Quick Facts</h5><ul><li>Son of Alex Breckenridge and Elizabeth Blackwell</li><li>Has two siblings, Craig and Keith</li><li>Began gymnastics in 1999</li><li>Favorite event is horizontal bar</li><li>Hobbies include traveling and reading</li><li>Favorite music genre is rap/hip hop</li><li>Favorite movies are Invictus and Skyfall</li><li>Favorite TV show is Psych</li><li>Favorite food is pad thai.</li></ul><h5>Career Highlights</h5><ul><li>Pan American Games, Lima, 2019 (Team - Men, Parallel Bars - Men, Horizontal Bar - Men)</li></ul><h5>More</h5>USA Gymnastics",
        "image": [
          {
            "secure_url": "https://res.cloudinary.com/usopc-prod/image/upload/v1679693702/TeamUSA%20Assets/Athlete%20Profiles/AthleteHeroDefault-1200x300.jpg"
          }
        ]
      },
      "medals": {
        "bronze": 0,
        "gold": 0,
        "silver": 0
      },
      "olympic_paralympic": "Team USA",
      "sport": [
        {
          "title": "Gymnastics",
          "type": "Olympic",
          "season": "Summer"
        }
      ],
      "olympian_paralympian_years": "",
      "olympian_paralympian_qualified": null,
      "para_classification": null,
      "hero_image": [],
      "featured_image_list": [],
      "thumbnail_image_list": [
        {
          "secure_url": "https://res.cloudinary.com/usopc-prod/image/upload/v1680013403/TeamUSA%20Assets/Athlete%20Profiles/Grant%20Breckenridge%20865210/breckenridge_grant.jpg"
        }
      ],
      "content_tags": [
        {
          "title": "Grant Breckenridge 865210"
        }
      ]
    },
    {
      "first_name": "Sam",
      "last_name": "Bredenbeck",
      "bio": {
        "height": "6'",
        "birthday": "1996-03-05T00:00:00",
        "hometown": {
          "city": "Beaverton",
          "state": "OR",
          "country": "United States",
          "latitude": 45.4874,
          "longitude": -122.8035
        },
        "education": "Forest Lake High School Oregon State University",
        "fun_fact": null,
        "biography": "<h5>Quick Facts</h5><ul><li>Son to Bill and Karen Bredenbeck</li><li>Brother to Jake Bredenbeck</li><li>Founder of Forza Performance (Personal &amp; Sports Performance Training)</li><li>Co-Founder of Beast Made Clothing</li><li>Three Time Junior National Champion and Male Athlete of the Year</li><li>Hobbies include spending time with family and playing sports.</li></ul><h5> World Championship Experience</h5><ul><li>Most recent: 2022 – bronze (Doubles - Men, Team - Men, Team - Mixed)</li><li>Years of participation: Doubles - Men 2022; Team - Men 2022; Team - Mixed 2022</li><li>Medals: 3 (3 bronze)</li><ul><li>Bronze – 2022 (Doubles - Men, Team - Men, Team - Mixed)</li></ul></ul>",
        "image": [
          {
            "secure_url": "https://res.cloudinary.com/usopc-prod/image/upload/v1686320778/TeamUSA%20Assets/Migration/Athlete%20Profiles/AthleteHeroDefault-1200x300.jpg"
          }
        ]
      },
      "medals": {
        "bronze": 0,
        "gold": 0,
        "silver": 0
      },
      "olympic_paralympic": "Team USA",
      "sport": [
        {
          "title": "Racquetball",
          "type": "Olympic",
          "season": "Summer"
        }
      ],
      "olympian_paralympian_years": "",
      "olympian_paralympian_qualified": null,
      "para_classification": null,
      "hero_image": [],
      "featured_image_list": [],
      "thumbnail_image_list": [
        {
          "secure_url": "https://res.cloudinary.com/usopc-prod/image/upload/v1687365685/TeamUSA%20Assets/Migration/Athlete%20Profiles/Sam%20Bredenbeck/SamBredenbeck_2022Headshot.jpg"
        }
      ],
      "content_tags": [
        {
          "title": "Sam Bredenbeck"
        }
      ]
    },
    {
      "first_name": "Jake",
      "last_name": "Bredenbeck",
      "bio": {
        "height": "6'2\"",
        "birthday": "1991-09-27T00:00:00",
        "hometown": {
          "city": "Marine on St. Croix",
          "state": "MN",
          "country": "United States",
          "latitude": 45.1833,
          "longitude": -92.8
        },
        "education": "Forest Lake High School (Forest Lake, Minn.) ‘09 Colorado State University—Pueblo ‘13",
        "fun_fact": null,
        "biography": "<h5>Quick Facts</h5><ul><li><span>Son of William and Karen Bredenbeck</span></li><li>Has one sibling, Sam, who plays racquetball as well.</li><li>Co-Owner ODISI Apparel</li><li>Co-Owner Countryside Carpentry</li><li>Loves spending time with family, friends, and playing about any sport he can.</li></ul><h5>Career Highlights</h5><ul><li>Pan American Games, Lima, 2019 (Team - Men, Singles - Men)</li><li>Pan American Games, Toronto, 2015 (Team - Men, Singles - Men)</li></ul><h5>World Championships Experience</h5><ul><li>Most recent: 2021 – 5th (Singles - Men)</li><li>Years of participation: Singles - Men 2021; Doubles - Men 2016</li><li>Medals: 1 (1 silver)</li><ul><li>Silver – 2016 (Doubles - Men)</li></ul></ul>",
        "image": [
          {
            "secure_url": "https://res.cloudinary.com/usopc-prod/image/upload/v1687365675/TeamUSA%20Assets/Migration/Athlete%20Profiles/Jake%20Bredenbeck/JakeForehand.jpg"
          }
        ]
      },
      "medals": {
        "bronze": 0,
        "gold": 0,
        "silver": 0
      },
      "olympic_paralympic": "Team USA",
      "sport": [
        {
          "title": "Racquetball",
          "type": "Olympic",
          "season": "Summer"
        }
      ],
      "olympian_paralympian_years": "",
      "olympian_paralympian_qualified": "",
      "para_classification": "",
      "hero_image": [],
      "featured_image_list": [],
      "thumbnail_image_list": [
        {
          "secure_url": "https://res.cloudinary.com/usopc-prod/image/upload/v1687365679/TeamUSA%20Assets/Migration/Athlete%20Profiles/Jake%20Bredenbeck/JakeBredenbeck_2022Headshot.jpg"
        }
      ],
      "content_tags": [
        {
          "title": "Jake Bredenbeck"
        }
      ]
    },
    {
      "first_name": "Drew",
      "last_name": "Bremer",
      "bio": {
        "height": "6'2\"",
        "birthday": "1995-11-22T00:00:00",
        "hometown": {
          "city": "Grand Rapids",
          "state": "MI",
          "country": "United States",
          "latitude": 42.96336,
          "longitude": -85.66809
        },
        "education": "East Grand Rapids High School (Grand Rapids, Mich.) ’13 Kalamazoo College ’17, Economics, Clemson Univeristy ’19, Applied Economics",
        "fun_fact": null,
        "biography": "<h5>Quick Facts</h5><ul><li>Son of Greg and Lisa</li><li>Has three siblings, Ally, Anna and Austin</li><li>Was born with hemiplegic cerebral palsy, a condition which affects the right side of his body</li><li>Participated in a number of sports growing up, including hockey, basketball, baseball and swimming</li><li>Played soccer at Kalamazoo College on the first team as a central defender</li><li>Was invited to train with the national team at a training camp and earned a spot on the team roster</li><li>Prior to becoming a member of the U.S. national team, had flown only once in his life</li><li>Hobbies include listening to country music and hanging out with friends.</li></ul><h5>Paralympic Experience </h5><ul><li>1-time Paralympian</li><ul><li>Paralympic Games Rio de Janeiro 2016, 7th (Team - Men)</li></ul></ul><h5> World Championship Experience</h5><ul><li>Most recent: 2022 – 4th (Team - Men)</li><li>Years of participation: Team - Men 2017, 2019, 2022</li><li>Top finish: 4th – 2022 (Team - Men)</li></ul><h5>More</h5><p>U.S. Soccer</p>",
        "image": [
          {
            "secure_url": "https://res.cloudinary.com/usopc-prod/image/upload/v1686320778/TeamUSA%20Assets/Migration/Athlete%20Profiles/AthleteHeroDefault-1200x300.jpg"
          }
        ]
      },
      "medals": {
        "bronze": 0,
        "gold": 0,
        "silver": 0
      },
      "olympic_paralympic": "Paralympian",
      "sport": [
        {
          "title": "Soccer",
          "type": "Olympic",
          "season": "Summer"
        }
      ],
      "olympian_paralympian_years": "Paralympian 2016",
      "olympian_paralympian_qualified": null,
      "para_classification": "FT7",
      "hero_image": [],
      "featured_image_list": [],
      "thumbnail_image_list": [
        {
          "secure_url": "https://res.cloudinary.com/usopc-prod/image/upload/v1686335810/TeamUSA%20Assets/Migration/Athlete%20Profiles/Drew%20Bremer/Bremer_Andrew_150x250.jpg"
        }
      ],
      "content_tags": [
        {
          "title": "Drew Bremer"
        }
      ]
    },
    {
      "first_name": "Rosie",
      "last_name": "Brennan",
      "bio": {
        "height": "5'6\"",
        "birthday": "1988-12-02T00:00:00",
        "hometown": {
          "city": "Park City",
          "state": "UT",
          "country": "United States",
          "latitude": 40.6461,
          "longitude": -111.4979
        },
        "education": "Alaska Pacific University ‘17",
        "fun_fact": "",
        "biography": "<h5>Quick Facts</h5><ul><li>Daughter of Wiggy and Tom Brennan</li><li>Has a twin, Charlie</li><li>Began skiing when she was 14</li><li>Would like to become a teacher before pursuing a more advanced geography degree to eventually work in dam removal</li><li>Volunteers with Fast and Female, a program dedicated to empowering young women through sport</li><li>Hobbies include baking, painting, camping, biking, hiking and running<span></span></li></ul><h5><span style='font-size: 11pt;'>Biographical Information</span></h5><p><span style='font-size: 11pt;'>Rosie Brennan grew up in a family and community that cherished outdoor recreation and alpine skiing. Her mother encouraged her to try cross-country skiing in eighth grade, a year after she watched the Olympic Winter Games Salt Lake City 2002. Though she began the sport later than most elite athletes, Brennan quickly found her path forward. She graduated from Park City High School and went on to compete for Dartmouth College, where she earned a degree in geography while racing on the collegiate circuit.</span></p><p><span style='font-size: 11pt;'>After college, Brennan relocated to Anchorage to train with the Alaska Pacific University Nordic Ski Center while pursuing a master's degree in education. Her graduate work focused on developing ski curriculum for rural Alaska, reflecting her commitment to expanding access to winter sports. She credits APU coach Erik Flora with helping her persevere through setbacks, including being cut from the U.S. Ski Team multiple times and battling injuries.&nbsp;</span></p><p><span style='font-size: 11pt;'>Brennan achieved a breakthrough moment in December 2020 when she won back-to-back world cup races in Davos, Switzerland at age 32. She became the first American to simultaneously hold the overall world cup leader's bib, world cup sprint leader's bib and world cup distance leader's bib, demonstrating her versatility across both sprint and distance events in classic and freestyle techniques.&nbsp;</span></p><p><span style='font-size: 11pt;'>Brennan competed in all six cross-country ski events at the Olympic Winter Games Beijing 2022, finishing fourth in the freestyle sprint — less than one second from a medal — and recording top-15 finishes across all her races. She has represented the United States at multiple world championships and Olympic Winter Games, contributing to Team USA's rise in international cross-country skiing.</span></p><p><span style='font-size: 11pt;'>Beyond competition, Brennan dedicates herself to developing the next generation of athletes. She serves as an ambassador for Fast and Female, empowering young women through sport, and volunteers with Skiku, which provides Nordic ski instruction to children and communities throughout rural Alaska. Her master's thesis focused on creating accessible ski curriculum for teachers in remote communities, combining her passion for education with her love of the sport. Through her volunteer work and competitive achievements, Brennan continues to inspire young athletes while representing American cross-country skiing at the highest level.</span></p><h5>Olympic Experience</h5><ul><li>3-time Olympian</li><ul><li>Olympic Games Milan 2026, 5th (4 x 7.5km Relay - Women), 15th (50km Classic Style - Women), 37th (2 x 10km Skiathlon - Women)</li><li>Olympic Games Beijing 2022, 4th (Sprint Freestyle - Women), 5th (Team Sprint Classic Style - Women), 6th (30km Freestyle - Women, 4 x 5km Relay - Women), 13th (10km Classic Style - Women), 14th (2 x 7.5km Skiathlon - Women)</li><li>Olympic Games Pyeongchang 2018, 58th (2 x 7.5km Skiathlon - Women)</li></ul></ul><h5>World Championships Experience</h5><ul><li>Most recent: 2025 – 6th (4 x 7.5km Relay - Women), 22th (10km Classic Style - Women), 30th (Sprint Freestyle - Women)</li><li>Years of participation: 10km Classic Style - Women 2017, 2019, 2025; 4 x 7.5km Relay - Women 2025; Sprint Freestyle - Women 2025; 10km Freestyle - Women 2021, 2023; 2 x 7.5km Skiathlon - Women 2015, 2017, 2019, 2023; 30km Classic Style - Women 2015, 2023; 4 x 5km Relay - Women 2015, 2019, 2021, 2023; Sprint Classic Style - Women 2021, 2023; Team Sprint Freestyle - Women 2021; 30km Freestyle - Women 2019</li><li>Top finish: 4th – 2015 (4 x 5km Relay - Women), 2021 (4 x 5km Relay - Women)</li></ul>",
        "image": [
          {
            "secure_url": "https://res.cloudinary.com/usopc-prod/image/upload/v1770335949/Brennan_R_bio_867569.png"
          }
        ]
      },
      "medals": {
        "bronze": 0,
        "gold": 0,
        "silver": 0
      },
      "olympic_paralympic": "Olympian",
      "sport": [
        {
          "title": "Cross-Country Skiing",
          "type": "Olympic",
          "season": "Winter"
        }
      ],
      "olympian_paralympian_years": "Olympian 2018, 2022, 2026",
      "olympian_paralympian_qualified": "Milano Cortina 2026",
      "para_classification": "",
      "hero_image": [
        {
          "secure_url": "https://res.cloudinary.com/usopc-prod/image/upload/v1770336307/Brennan_R_main_867569.png"
        }
      ],
      "featured_image_list": [],
      "thumbnail_image_list": [
        {
          "secure_url": "https://res.cloudinary.com/usopc-prod/image/upload/v1686923972/TeamUSA%20Assets/Migration/Athlete%20Profiles/Rosie%20Brennan/Brennan_Rosie_Headshot_2022_150x250.jpg"
        }
      ],
      "content_tags": [
        {
          "title": "Rosie Brennan"
        },
        {
          "title": "Beijing 2022"
        },
        {
          "title": "Cross-Country Skiing"
        },
        {
          "title": "2024-2025 National Team Tag"
        },
        {
          "title": "2025-2026 National Team"
        },
        {
          "title": "Olympic Winter Games Milano Cortina 2026, Qualified"
        }
      ]
    },
    {
      "first_name": "Josh",
      "last_name": "Brewer",
      "bio": {
        "height": "3'5\"",
        "birthday": "1995-09-10T00:00:00",
        "hometown": {
          "city": "Battle Ground",
          "state": "WA",
          "country": "United States",
          "latitude": 45.7837,
          "longitude": -122.5326
        },
        "education": "Battle Ground High School (Battle Ground, Wash.) ‘15 ",
        "fun_fact": null,
        "biography": "<h5>Quick Facts</h5><ul><li>Brewer is a triple amputee who was run over by a train while living in the streets of Ethiopia as a child. He spent months in a hospital after losing both legs from below the knees and his right arm from below the elbow</li><li>Son of Laura Brewer</li><li>Has one brother, Josiah</li><li>Has lived in three countries, Ethiopia, Australia and the U.S</li><li>Enjoys fishing, basketball and relaxing.</li></ul><h5>Career Highlights</h5><ul>\r\n                            <li>2016 Canada Cup</li>\r\n                    </ul><h5>Paralympic Experience</h5><ul><li>1-time Paralympian; 1-time Paralympic medalist (1 silver)</li><ul><li>Paralympic Games Rio de Janeiro 2016, silver (Team - Mixed)</li></ul></ul>",
        "image": [
          {
            "secure_url": "https://res.cloudinary.com/usopc-prod/image/upload/v1682699863/TeamUSA%20Assets/Migration/Athlete%20Profiles/Josh%20Brewer%201006913/AthleteHeroDefault-1200x300.jpg"
          }
        ]
      },
      "medals": {
        "bronze": 0,
        "gold": 0,
        "silver": 1
      },
      "olympic_paralympic": "Paralympian",
      "sport": [
        {
          "title": "Wheelchair Rugby",
          "type": "Paralympic",
          "season": "Summer"
        }
      ],
      "olympian_paralympian_years": "Paralympian 2016",
      "olympian_paralympian_qualified": null,
      "para_classification": "3.5",
      "hero_image": [],
      "featured_image_list": [],
      "thumbnail_image_list": [
        {
          "secure_url": "https://res.cloudinary.com/usopc-prod/image/upload/v1682699865/TeamUSA%20Assets/Migration/Athlete%20Profiles/Josh%20Brewer%201006913/Brewer_Joshua_150x250.jpg"
        }
      ],
      "content_tags": [
        {
          "title": "Josh Brewer 1006913"
        }
      ]
    },
    {
      "first_name": "Brittany",
      "last_name": "Brewer",
      "bio": {
        "height": "6'5\"",
        "birthday": "1997-11-06T00:00:00",
        "hometown": {
          "city": "Abilene",
          "state": "TX",
          "country": "United States",
          "latitude": 32.4503,
          "longitude": -99.7331
        },
        "education": "Wylie High School (Abilene, Texas) ‘16 Texas Tech University ‘20, Community, Family and Addiction Sciences",
        "fun_fact": null,
        "biography": "<h5>Quick Facts</h5><ul><li>Daughter of Jacob and Melanie Brewer</li><li>Sister to Brianna, Brooklyn, Joy and Josh</li><li>Uncle Mike Smith also competed at Texas Tech as a linebacker for the football team</li><li>Hobbies include photography, a skill she utilizes to take her teammates’ senior portraits every year</li><li>Enjoys hiking, painting, drawing and reading.</li></ul><h5>Career Highlights</h5><ul><li>Pan American Games, Lima, 2019 (Team - Women)</li></ul><h5>More</h5>USA Basketball",
        "image": [
          {
            "secure_url": "https://res.cloudinary.com/usopc-prod/image/upload/v1679693702/TeamUSA%20Assets/Athlete%20Profiles/AthleteHeroDefault-1200x300.jpg"
          }
        ]
      },
      "medals": {
        "bronze": 0,
        "gold": 0,
        "silver": 0
      },
      "olympic_paralympic": "Team USA",
      "sport": [
        {
          "title": "Basketball",
          "type": "Olympic",
          "season": "Summer"
        }
      ],
      "olympian_paralympian_years": "",
      "olympian_paralympian_qualified": null,
      "para_classification": null,
      "hero_image": [],
      "featured_image_list": [],
      "thumbnail_image_list": [
        {
          "secure_url": "https://res.cloudinary.com/usopc-prod/image/upload/v1680013383/TeamUSA%20Assets/Athlete%20Profiles/Brittany%20Brewer%201155913/brewer_brittany.jpg"
        }
      ],
      "content_tags": [
        {
          "title": "Brittany Brewer 1155913"
        }
      ]
    },
    {
      "first_name": "Matthew",
      "last_name": "Brewer",
      "bio": {
        "height": "5'9\"",
        "birthday": "1975-05-08T00:00:00",
        "hometown": {
          "city": "Huntington Beach",
          "state": "CA",
          "country": "United States",
          "latitude": 33.6902,
          "longitude": -118.0074
        },
        "education": "Saddleback Community College ",
        "fun_fact": "Hobbies include snowboarding, outdoor recreation, mentoring adaptive athletes and crafting prosthetics",
        "biography": "<h5><span style=\"font-size: 11pt;\">Quick Facts</span></h5><ul><li><span style=\"font-size: 11pt;\"><strong>Specialty:&nbsp;</strong></span><span style=\"font-size: 11pt;\">Para Alpine Skiing (Sitting) — LW12-2 Classification</span></li><li><span style=\"font-size: 11pt;\">Former nationally ranked USASA snowboarder</span></li><li><span style=\"font-size: 11pt;\">Bilateral above-knee amputee due to Compartment Syndrome</span></li><li><span style=\"font-size: 11pt;\">Hobbies include snowboarding, outdoor recreation, mentoring adaptive athletes and crafting prosthetics</span></li></ul><h5><span style=\"font-size: 11pt;\">Biographical Information</span></h5><p><span style=\"font-size: 11pt;\">Growing up in Huntington Beach, California, Matthew Brewer was very athletic, enjoying surfing, skateboarding, BMX biking and snowboarding. He was a competitive snowboarder who reached national ranking in the United States of America Snowboard and Freeski Association (USASA) in the late 1990s. However, in 2008, Brewer was diagnosed with testicular cancer. He faced surgery, chemotherapy, daily nausea and extreme pain. He also developed Compartment Syndrome in his legs, a condition in which pressure builds within a closed muscle compartment, cutting off blood supply. The damage was severe enough to require amputation of both legs above the knee.&nbsp;</span></p><p><span style=\"font-size: 11pt;\">The process of adaptation was gradual. A pivotal moment came when Brewer attended a camp specifically designed for bilateral above-knee amputees and met Paralympian Stephani Victor. Victor's account of her own Paralympic journey struck him as something real and achievable. Her invitation to learn to ski on a sit-ski set a new course. He initially moved to Park City to try adaptive snowboarding but found his true passion in monoskiing. Brewer applied for a Challenged Athletes Foundation (CAF) grant to help offset the cost of specialized sit-ski equipment, relocated to Utah, and enrolled with the National Ability Center's High Performance Team in Park City. He began building his ski racing career from the bottom.&nbsp;</span></p><p><span style=\"font-size: 11pt;\">His commitment and character within the program earned him the National Ability Center High Performance Team Sportsman of the Year award for the 2020–21 season. On the Nor-Am circuit that same season, he finished 5th in slalom and 6th in giant slalom. Brewer made his Paralympic debut at the Paralympic Winter Games Beijing 2022, finishing 12th in slalom and 25th in giant slalom in the sitting division. He continued his international development at the 2023 FIS Para Alpine Skiing World Championships, where he posted 9th place in alpine combined and returned in 2025 to finish 15th in slalom and 17th in giant slalom.</span></p><p><span style=\"font-size: 11pt;\">Beyond racing, Brewer has dedicated himself to expanding opportunities for adaptive athletes. He mentors new monoskiers, volunteers extensively with the Amputee Coalition, works part-time at Hanger Clinic and travels for speaking engagements at hospitals and events.</span></p><h5>Paralympic Experience</h5><ul><li>2-time Paralympian</li><ul><li>Paralympic Games Milan 2026,  (Slalom - Sitting - Men, Super Combined - Sitting - Men), 12th (Giant Slalom - Sitting - Men), 16th (Super-G - Sitting - Men)</li><li>Paralympic Games Beijing 2022, 12th (Slalom - Sitting - Men), 25th (Giant Slalom - Sitting - Men)</li></ul></ul><h5>World Championships Experience</h5><ul><li>Most recent: 2025 – 15th (Slalom - Sitting - Men), 17th (Giant Slalom - Sitting - Men)</li><li>Years of participation: Giant Slalom - Sitting - Men 2023, 2025; Slalom - Sitting - Men 2023, 2025; Downhill - Sitting - Men 2023; Super Combined - Sitting - Men 2023; Super-G - Sitting - Men 2023</li><li>Top finish:  – 2023 (Slalom - Sitting - Men)</li></ul>",
        "image": [
          {
            "secure_url": "https://res.cloudinary.com/usopc-prod/image/upload/v1687661959/TeamUSA%20Assets/Athlete%20Profiles/batch%20images/Brewer_m_bio_.png"
          }
        ]
      },
      "medals": {
        "bronze": 0,
        "gold": 0,
        "silver": 0
      },
      "olympic_paralympic": "Paralympian",
      "sport": [
        {
          "title": "Para Alpine Skiing",
          "type": "Paralympic",
          "season": "Winter"
        }
      ],
      "olympian_paralympian_years": "Paralympian 2022, 2026",
      "olympian_paralympian_qualified": "Milano Cortina 2026",
      "para_classification": "12-2, Sitting",
      "hero_image": [
        {
          "secure_url": "https://res.cloudinary.com/usopc-prod/image/upload/v1687662184/TeamUSA%20Assets/Athlete%20Profiles/batch%20images/Brewer_m_hero_.png"
        }
      ],
      "featured_image_list": [
        {
          "secure_url": "https://res.cloudinary.com/usopc-prod/image/upload/v1772995114/Brewer_M_featured_1232411.png"
        }
      ],
      "thumbnail_image_list": [
        {
          "secure_url": "https://res.cloudinary.com/usopc-prod/image/upload/v1687366729/TeamUSA%20Assets/Migration/Athlete%20Profiles/Matthew%20Brewer/Brewer_Matthew_Headshot_2022_150x250.png"
        }
      ],
      "content_tags": [
        {
          "title": "Matthew Brewer"
        },
        {
          "title": "Beijing 2022"
        },
        {
          "title": "Para Alpine Skiing"
        },
        {
          "title": "Paralympic Winter Games Milano Cortina 2026, Qualified"
        }
      ]
    },
    {
      "first_name": "Morgan",
      "last_name": "Brian",
      "bio": {
        "height": "5'7\"",
        "birthday": "1993-02-26T00:00:00",
        "hometown": {
          "city": "Simons Island",
          "state": "GA",
          "country": "United States",
          "latitude": 31.1494,
          "longitude": -81.3908
        },
        "education": "Frederica Academy (St. Simons Island, Ga.) ‘11 University of Virginia ‘14, Kinesiology ",
        "fun_fact": null,
        "biography": "<h5>Quick Facts</h5><ul><li>Daughter of Steve and Vickie Brian</li><li>Has one older sister, Jennifer</li><li>Selected No. 1 overall by the Houston Dash in the 2015 NWSL Draft</li><li>Grew up on St. Simon’s Island, a tiny barrier island off the coast of Georgia, three miles wide, 11 miles long</li><li>Hometown has a strong soccer culture, but with a small population, she was forced to play against kids that were 4-5 years older</li><li>Nicknames are “Moe,” “Miss M” and “Bean”</li><li>Enjoys playing ping-pong and basketball, watching movies, going to the beach and attending church</li><li>Named 2014 U.S. Soccer Young Female Athlete of the Year.</li></ul><h5>Olympic Experience </h5><ul><li>1-time Olympian</li><ul><li>Olympic Games Rio de Janeiro 2016, 5th (Team - Women)</li></ul></ul><h5> World Championship Experience</h5><ul><li>Most recent: 2019 – gold (Team - Women)</li><li>Years of participation: Team - Women 2015, 2019</li><li>Medals: 2 (2 gold)</li><ul><li>Gold – 2019 (Team - Women);  2015 (Team - Women)</li></ul></ul><h5>More</h5>Personal Website<br>\nU.S. Soccer",
        "image": [
          {
            "secure_url": "https://res.cloudinary.com/usopc-prod/image/upload/v1682699851/TeamUSA%20Assets/Migration/Athlete%20Profiles/Morgan%20Brian%20819630/AthleteHeroDefault-1200x300.jpg"
          }
        ]
      },
      "medals": {
        "bronze": 0,
        "gold": 0,
        "silver": 0
      },
      "olympic_paralympic": "Olympian",
      "sport": [
        {
          "title": "Soccer",
          "type": "Olympic",
          "season": "Summer"
        }
      ],
      "olympian_paralympian_years": "Olympian 2016",
      "olympian_paralympian_qualified": null,
      "para_classification": null,
      "hero_image": [],
      "featured_image_list": [],
      "thumbnail_image_list": [
        {
          "secure_url": "https://res.cloudinary.com/usopc-prod/image/upload/v1682699852/TeamUSA%20Assets/Migration/Athlete%20Profiles/Morgan%20Brian%20819630/Brian_Morgan_150x250.jpg"
        }
      ],
      "content_tags": [
        {
          "title": "Morgan Brian 819630"
        }
      ]
    },
    {
      "first_name": "Jaclyn",
      "last_name": "Briggs",
      "bio": {
        "height": "5'6\"",
        "birthday": "1988-05-23T00:00:00",
        "hometown": {
          "city": "Robesonia",
          "state": "PA",
          "country": "United States",
          "latitude": 40.3606,
          "longitude": -76.1627
        },
        "education": "Conrad Weiser High School '06 University of North Carolina '10",
        "fun_fact": null,
        "biography": "<h5>Quick Facts</h5><ul><li>Daughter of Dean and Roxanne Kintzer</li><li>Wife to Michael Briggs</li><li>Has two dogs named London and Blue</li></ul><h5>Career Highlights</h5><ul>\r\n                            <li>2018: Retired from the U.S. Women&#39;s National Team with 184 international caps</li>\r\n                            <li>2018: Series against The Netherlands (Palo Alto, Calif.), Series against Canada (Chula Vista, Calif.), Series against Chile (Lancaster, Pa.), Series against Argentina (Tucuman, Argentina)</li>\r\n                            <li>2017 : The Hawke&#39;s Bay Cup (4th, Hawke&#39;s Bay, New Zealand), Series against Ireland (Lancaster, Pa.), International Festival of Hockey (4th, Melbourne, Australia), Nominated for 2017 FIH Hockey Stars Awards Female Goalkeeper of the Year Award</li>\r\n                            <li>2016: Series against Canada (Chula Vista, Calif.), Series against Chile (Lancaster, Pa.), Series against Holland (Hilversum, The Netherlands), Citi Rio Send-Off Series (Lancaster, Pa.), Nominated for 2016 FIH Hockey Stars Awards Female Goalkeeper of the Year Award</li>\r\n                            <li>2015: Series against Argentina (Lancaster, Pa.), 8 Nations Tournament (5th, Hawke&#39;s Bay, New Zealand), Series against Ireland (Lancaster, Pa.), Series against Great Britain (Marlow, England), Series against Japan (Lancaster, Pa.)</li>\r\n                            <li>2013: Four Nations (Auckland, New Zealand)</li>\r\n                            <li>2010: Joined the U.S. Women&#39;s National Team</li>\r\n                            <li>2009: Junior World Cup (Boston, Mass.)</li>\r\n                            <li>2008: Pan American Junior Championships (1st, Mexico City, Mexico)</li>\r\n                    </ul><h5>Olympic Experience </h5><ul><li>1-time Olympian</li><ul><li>Olympic Games Rio de Janeiro 2016, 5th (Team - Women)</li></ul></ul><h5> World Championship Experience</h5><ul><li>Gold - 2017 World League Semifinals (Johannesburg, South Africa), Named Best Goalkeeper of the Tournament</li><li>Gold - 2015 Pan American Games ( Toronto, Canada)</li><li>Gold - 2014 Champions Challenge (Glasgow, Scotland)</li><li>Gold - 2013 World League Round 2 (Rio de Janeiro, Brazil)</li><li>Gold - 2011 Pan American Games (Guadalajara, Mexico)</li><li>Silver - 2012 Champions Challenge I (Dublin, Ireland)</li><li>Bronze - 2017 Pan American Cup (Lancaster, Pa.)</li><li>Bronze - 2016 Champions Trophy (London, England)</li><li>5th - 2015 World League Round Semifinals (Valencia, Spain)</li><li>4th - 2014 Rabobank Hockey World Cup (The Hague, Netherlands)</li><li>7th - 2017 World League Final (Auckland, New Zealand)</li><li>14th - 2018 Vitality Hockey Women's World Cup (London, England)</li></ul><h5>More</h5>As a rising superstar goalkeeper, Briggs helped the Tar Heels win two NCAA titles before joining the U.S. National Team in 2010 and making field hockey a career. Originally left off the 2011 Pan American Games roster, Briggs received a phone call a mere day prior to the start of the Olympic qualification tournament with a voice on the other end telling her to pack her bags and hop on the next flight to Guadalajara. Briggs helped Team USA defeat Argentina to win its first Pan American gold medal and earn a berth in the 2012 Olympics in London. Briggs was a member of the gold medal Champions Challenge squad and a part of the U.S. squad that stunned the world with a fourth place finish at the 2014 Rabobank Hockey World Cup.<br>",
        "image": [
          {
            "secure_url": "https://res.cloudinary.com/usopc-prod/image/upload/v1682699878/TeamUSA%20Assets/Migration/Athlete%20Profiles/Jaclyn%20Briggs%20805258/AthleteHeroDefault-1200x300.jpg"
          }
        ]
      },
      "medals": {
        "bronze": 0,
        "gold": 0,
        "silver": 0
      },
      "olympic_paralympic": "Olympian",
      "sport": [
        {
          "title": "Field Hockey",
          "type": "Olympic",
          "season": "Summer"
        }
      ],
      "olympian_paralympian_years": "Olympian 2016",
      "olympian_paralympian_qualified": null,
      "para_classification": null,
      "hero_image": [],
      "featured_image_list": [],
      "thumbnail_image_list": [
        {
          "secure_url": "https://res.cloudinary.com/usopc-prod/image/upload/v1682699880/TeamUSA%20Assets/Migration/Athlete%20Profiles/Jaclyn%20Briggs%20805258/Briggs_150x250.jpg"
        }
      ],
      "content_tags": [
        {
          "title": "Jaclyn Briggs 805258"
        }
      ]
    },
    {
      "first_name": "Jack",
      "last_name": "Briggs",
      "bio": {
        "height": "5'7\"",
        "birthday": "1998-07-01T00:00:00",
        "hometown": {
          "city": "Fort Collins",
          "state": "CO",
          "country": "United States",
          "latitude": 40.5853,
          "longitude": -105.0844
        },
        "education": "Fort Collins High School (Fort Collins, Colo.) ‘17 Colorado Mesa University (Grand Junction, Colo.) ’20, Marketing",
        "fun_fact": null,
        "biography": "<h5>Quick Facts</h5><ul><li>Son of Katie and Randy  Briggs</li><li>Has a brother, Henry, and a sister, Sofia</li><li>Born without a lower left arm below the elbow</li><li>Runs on the track and field team at Colorado Mesa University</li><li>Played golf and football before focusing on track</li><li>Hobbies include playing video games, hanging out with friends, rollerblading and golf.</li></ul><h5> World Championship Experience</h5><ul><li>Most recent: 2019 – 9th (100m T47 - Men)</li><li>Years of participation: 100m T47 - Men 2015, 2017, 2019; 200m T47 - Men 2015, 2017</li><li>Top finish: 9th – 2017 (200m T47 - Men), 2019 (100m T47 - Men)</li></ul><h5>Career Highlights</h5><ul><li>ParaPan American Games, Lima, 2019 (100m T47 - Men)</li><li>ParaPan American Games, Toronto, 2015 (100m T47 - Men)</li></ul>",
        "image": [
          {
            "secure_url": "https://res.cloudinary.com/usopc-prod/image/upload/v1679693702/TeamUSA%20Assets/Athlete%20Profiles/AthleteHeroDefault-1200x300.jpg"
          }
        ]
      },
      "medals": {
        "bronze": 0,
        "gold": 0,
        "silver": 0
      },
      "olympic_paralympic": "Team USA",
      "sport": [
        {
          "title": "Para Track and Field",
          "type": "Paralympic",
          "season": "Summer"
        }
      ],
      "olympian_paralympian_years": "",
      "olympian_paralympian_qualified": null,
      "para_classification": "T46",
      "hero_image": [],
      "featured_image_list": [],
      "thumbnail_image_list": [
        {
          "secure_url": "https://res.cloudinary.com/usopc-prod/image/upload/v1680013378/TeamUSA%20Assets/Athlete%20Profiles/Jack%20Briggs%20832712/Briggs_Jack_150x250.jpg"
        }
      ],
      "content_tags": [
        {
          "title": "Jack Briggs 832712"
        }
      ]
    },
    {
      "first_name": "Gregory",
      "last_name": "Brigman",
      "bio": {
        "height": "5'5\"",
        "birthday": "1987-02-27T00:00:00",
        "hometown": {
          "city": "Raeford",
          "state": "NC",
          "country": "United States",
          "latitude": 34.9907,
          "longitude": -79.2375
        },
        "education": " University of North Carolina-Charlotte ’13, Master of Civil Engineering ",
        "fun_fact": null,
        "biography": "<h5>Quick Facts</h5><ul><li>Brigman was born with cerebral palsy and as a child he wore a leg brace on his left side to attempt to correct his physical impairment. In the second grade, he underwent a major surgery and physical therapy with the University of North Carolina-Chapel Hill medical system to attempt to improve his cerebral palsy. After surgery, he went on to play youth club soccer and played four years at the varsity level in high school. As a senior, he received the recognition of All-Conference honors. He is a prominent National Collegiate Referee in the Carolina’s soccer community and officiate games for middle school, youth club, high school, college and recently games at the lower professional levels. Through his involvement in the soccer referee community, he found a referee administrator that knew the coach of the U.S. Paralympic National Soccer Team</li><li>Son of Gary and Kathy Brigman</li><li>Married to Louremy Brigman</li><li>Has one sister, Kathryn.</li></ul><h5>Career Highlights</h5><ul>\r\n                            <li>2016 Pre Paralympic Tournament, 6th</li>\r\n                    </ul><h5>Paralympic Experience </h5><ul><li>1-time Paralympian</li><ul><li>Paralympic Games Rio de Janeiro 2016, 7th (Team - Men)</li></ul></ul><h5>More</h5><p>U.S. Soccer</p><h5>World Championships Experience</h5><ul><li>Most recent: 2017 – 5th (Team - Men)</li><li>Years of participation: Team - Men 2017</li><li>Top finish: 5th – 2017 (Team - Men)</li></ul>",
        "image": [
          {
            "secure_url": "https://res.cloudinary.com/usopc-prod/image/upload/v1682699819/TeamUSA%20Assets/Migration/Athlete%20Profiles/Gregory%20Brigman%201006301/AthleteHeroDefault-1200x300.jpg"
          }
        ]
      },
      "medals": {
        "bronze": 0,
        "gold": 0,
        "silver": 0
      },
      "olympic_paralympic": "Paralympian",
      "sport": [
        {
          "title": "Soccer",
          "type": "Olympic",
          "season": "Summer"
        }
      ],
      "olympian_paralympian_years": "Paralympian 2016",
      "olympian_paralympian_qualified": null,
      "para_classification": "FT7",
      "hero_image": [],
      "featured_image_list": [],
      "thumbnail_image_list": [
        {
          "secure_url": "https://res.cloudinary.com/usopc-prod/image/upload/v1682699821/TeamUSA%20Assets/Migration/Athlete%20Profiles/Gregory%20Brigman%201006301/Brigman_Gregory_150x250.jpg"
        }
      ],
      "content_tags": [
        {
          "title": "Gregory Brigman 1006301"
        }
      ]
    },
    {
      "first_name": "Cameron",
      "last_name": "Brink",
      "bio": {
        "height": "6'4\"",
        "birthday": "2001-12-31T00:00:00",
        "hometown": {
          "city": "Beaverton",
          "state": "OR",
          "country": "United States",
          "latitude": 45.4874,
          "longitude": -122.8035
        },
        "education": "Stanford University '24",
        "fun_fact": null,
        "biography": "<h5>Quick Facts</h5><ul><li>Born in Princeton, N.J.</li><li>Daughter to Michelle Bain-Brink and Greg Brink</li><li>Sister to brother, Cy Brink</li><li>Attended Southridge High School (Beaverton, Ore.)</li><li><span>The Brinks are family friends with the Curry family</span></li></ul><h5>Career Highlights</h5><ul><li>World Championship U-19, Bangkok, 2019 (Team - Women)</li><li>World Championship U-17, Minsk, 2018 (Team - Women)</li></ul>",
        "image": [
          {
            "secure_url": "https://res.cloudinary.com/usopc-prod/image/upload/v1718342584/TeamUSA%20Assets/Athlete%20Profiles/Cameron%20Brink%201077635/brink_c_bio_1077635.png"
          }
        ]
      },
      "medals": {
        "bronze": 0,
        "gold": 0,
        "silver": 0
      },
      "olympic_paralympic": "Team USA",
      "sport": [
        {
          "title": "3x3 Basketball",
          "type": "Olympic",
          "season": "Summer"
        }
      ],
      "olympian_paralympian_years": "",
      "olympian_paralympian_qualified": "",
      "para_classification": "",
      "hero_image": [
        {
          "secure_url": "https://res.cloudinary.com/usopc-prod/image/upload/v1718342571/TeamUSA%20Assets/Athlete%20Profiles/Cameron%20Brink%201077635/brink_c_hero_1077635.png"
        }
      ],
      "featured_image_list": [
        {
          "secure_url": "https://res.cloudinary.com/usopc-prod/image/upload/v1718342571/TeamUSA%20Assets/Athlete%20Profiles/Cameron%20Brink%201077635/brink_c_hero_1077635.png"
        }
      ],
      "thumbnail_image_list": [
        {
          "secure_url": "https://res.cloudinary.com/usopc-prod/image/upload/v1718342571/TeamUSA%20Assets/Athlete%20Profiles/Cameron%20Brink%201077635/brink_c_hero_1077635.png"
        }
      ],
      "content_tags": [
        {
          "title": "Cameron Brink"
        },
        {
          "title": "Basketball"
        },
        {
          "title": "3x3 Basketball"
        },
        {
          "title": "Olympic Games Paris 2024, Qualified"
        }
      ]
    },
    {
      "first_name": "Joey",
      "last_name": "Brinson",
      "bio": {
        "height": "5'9\"",
        "birthday": "1976-08-22T00:00:00",
        "hometown": {
          "city": "Florence",
          "state": "MS",
          "country": "United States",
          "latitude": 32.1485,
          "longitude": -90.0915
        },
        "education": "Florence High School (Florence, Miss.) ‘18 Hinds Community College",
        "fun_fact": null,
        "biography": "<h5>Quick Facts</h5><ul><li>After a car accident at age 17 left Brinson a paraplegic, the former multi-sport high school athlete turned his attention to sled hockey before being recruited to compete in wheelchair fencing in 2006. Within just four years, he qualified for his first world championship team. Although he won medals in both foil and epee at the 2011 Pan American Wheelchair Championships, his specialty weapon – saber – wasn’t contested at the Paralympic qualifier. Brinson continued to fight his way through the World Cup circuit to build his world ranking and qualify for London</li><li>Son of Betty Clanton</li><li>Involved with peer support and other programs and activities in his local area</li><li>Hobbies include music, barbequing, fishing, hunting, archery, shooting and other recreational sports and activities.</li></ul><h5>Paralympic Experience </h5><ul><li>2-time Paralympian</li><ul><li>Paralympic Games Rio de Janeiro 2016, 10th (Individual Sabre B - Men)</li><li>Paralympic Games London 2012, 14th (Individual Sabre B - Men)</li></ul></ul><h5> World Championship Experience</h5><ul><li>Most recent: 2017 – 10th (Team Foil - Men), 18th (Individual Foil B - Men, Individual Sabre B - Men)</li><li>Years of participation: Individual Foil B - Men 2017; Individual Sabre B - Men 2010, 2011, 2013, 2015, 2017; Team Foil - Men 2017; Individual Epee B - Men 2010, 2011, 2013, 2015; Team Epee - Men 2010, 2011, 2013; Team Sabre - Men 2010, 2013</li><li>Top finish: 6th – 2010 (Team Sabre - Men)</li></ul><h5>More</h5><p>USA Fencing</p>",
        "image": [
          {
            "secure_url": "https://res.cloudinary.com/usopc-prod/image/upload/v1686320778/TeamUSA%20Assets/Migration/Athlete%20Profiles/AthleteHeroDefault-1200x300.jpg"
          }
        ]
      },
      "medals": {
        "bronze": 0,
        "gold": 0,
        "silver": 0
      },
      "olympic_paralympic": "Paralympian",
      "sport": [
        {
          "title": "Wheelchair Fencing",
          "type": "Paralympic",
          "season": "Summer"
        }
      ],
      "olympian_paralympian_years": "Paralympian 2012, 2016",
      "olympian_paralympian_qualified": "",
      "para_classification": "Category B",
      "hero_image": [],
      "featured_image_list": [],
      "thumbnail_image_list": [
        {
          "secure_url": "https://res.cloudinary.com/usopc-prod/image/upload/v1686335802/TeamUSA%20Assets/Migration/Athlete%20Profiles/Joey%20Brinson/brinson_joey_120x187.jpg"
        }
      ],
      "content_tags": [
        {
          "title": "Joey Brinson"
        }
      ]
    },
    {
      "first_name": "Brandon",
      "last_name": "Briones",
      "bio": {
        "height": "5'3\"",
        "birthday": "2001-04-29T00:00:00",
        "hometown": {
          "city": "Gilbert",
          "state": "AZ",
          "country": "United States",
          "latitude": 33.3528,
          "longitude": -111.789
        },
        "education": "Gilbert High School (Gilbert, Ariz.) ‘19 ",
        "fun_fact": null,
        "biography": "<h5>Quick Facts</h5><ul><li>Son of Deo and Laurie</li><li>Has two siblings, Natalie and Dylan, who both do gymnastics</li><li>Got involved in gymnastics in 2007 after teaching himself how to do a handstand and walk on his hands. His parents then decided to enroll him in gymnastics</li><li>Favorite event is floor</li><li>Hobbies include reading, swimming, solving puzzles and hiking</li><li>Favorite books are the Harry Potter series</li><li>Favorite school subject is biology</li><li>Enjoys rap, electronic music, the Walking Dead and the Office</li><li>Favorite foods are steak, noodles and Thai food</li><li>Can solve a Rubik’s cube in under a minute.</li></ul><h5>Career Highlights</h5><ul>\r\n                            <li>2018 U.S. Junior Gymnastics Championships, 1st (all-around, still rings, high bar), 3rd (floor, pommel horse, parallel bars), 6th (vault)</li>\r\n                            <li>2018 Junior Pan American Championships, 1st (team, all-around), 2nd (still rings, high bar), 3rd (vault), 6th (floor, pommel horse, parallel bars)</li>\r\n                            <li>2018 Men&#39;s Junior Olympic National Championships, 1st (all-around, still rings, parallel bars, high bar), 2nd (floor, pommel horse), 5th (vault)</li>\r\n                    </ul><h5>More</h5>USA Gymnastics",
        "image": [
          {
            "secure_url": "https://res.cloudinary.com/usopc-prod/image/upload/v1679693702/TeamUSA%20Assets/Athlete%20Profiles/AthleteHeroDefault-1200x300.jpg"
          }
        ]
      },
      "medals": {
        "bronze": 0,
        "gold": 0,
        "silver": 0
      },
      "olympic_paralympic": "Olympian",
      "sport": [
        {
          "title": "Gymnastics",
          "type": "Olympic",
          "season": "Summer"
        }
      ],
      "olympian_paralympian_years": "",
      "olympian_paralympian_qualified": null,
      "para_classification": null,
      "hero_image": [],
      "featured_image_list": [],
      "thumbnail_image_list": [
        {
          "secure_url": "https://res.cloudinary.com/usopc-prod/image/upload/v1680013397/TeamUSA%20Assets/Athlete%20Profiles/Brandon%20Briones%20878194/briones_brandon.jpg"
        }
      ],
      "content_tags": [
        {
          "title": "Brandon Briones 878194"
        }
      ]
    },
    {
      "first_name": "Matthew",
      "last_name": "Brisson",
      "bio": {
        "height": "5' 2\"",
        "birthday": "2008-11-15T00:00:00",
        "hometown": {
          "city": "Boynton Beach",
          "state": "FL",
          "country": "United States",
          "latitude": 26.5245,
          "longitude": -80.0667
        },
        "education": "St. Jude Catholic School",
        "fun_fact": null,
        "biography": "<h5>Quick Facts</h5><ul><li>Son of Michael and Carol Brisson</li><li>Has an older sister, Katie Rose</li><li>His aunt Therese Brisson won Olympic gold (2002) and silver (1998) as a member of Canada&#39;s women&#39;s hockey team</li><li>Started diving at age 8</li><li>Favorite dive is 105B on 7-meter and has started doing dives on 10-meter in preparation for the 2022 season</li><li>Qualified for his first junior nationals in 2018  but suffered a serious arm injury in a non-diving accident the night before he was supposed to leave for nationals</li><li>Had to have surgery and was in a cast for eight weeks; he refers to the prominent semi-circular scar as his &#39;shark bite scar&#39;</li><li>Enjoys online computer gaming, reading, drawing</li><li>Would like to design and program computer games one day</li><li>Says he seems to perform better if he gets a haircut before a meet</li></ul><h5>Career Highlights</h5><ul>\r\n                            <li>2021 Junior Pan American Championships team member (7th, platform)</li>\r\n                    </ul>",
        "image": [
          {
            "secure_url": "https://res.cloudinary.com/usopc-prod/image/upload/v1686320778/TeamUSA%20Assets/Migration/Athlete%20Profiles/AthleteHeroDefault-1200x300.jpg"
          }
        ]
      },
      "medals": {
        "bronze": 0,
        "gold": 0,
        "silver": 0
      },
      "olympic_paralympic": "Team USA",
      "sport": [
        {
          "title": "Diving",
          "type": "Olympic",
          "season": "Summer"
        }
      ],
      "olympian_paralympian_years": "",
      "olympian_paralympian_qualified": "",
      "para_classification": "",
      "hero_image": [],
      "featured_image_list": [],
      "thumbnail_image_list": [
        {
          "secure_url": "https://res.cloudinary.com/usopc-prod/image/upload/v1687362459/TeamUSA%20Assets/Migration/Athlete%20Profiles/Matthew%20Brisson/Matthew-Brisson_150x250.jpg"
        }
      ],
      "content_tags": [
        {
          "title": "Matthew Brisson"
        }
      ]
    },
    {
      "first_name": "Brendan",
      "last_name": "Brisson",
      "bio": {
        "height": "6'0\"",
        "birthday": "2001-10-22T00:00:00",
        "hometown": {
          "city": "Manhattan Beach",
          "state": "CA",
          "country": "United States",
          "latitude": 33.8842,
          "longitude": -118.4106
        },
        "education": " University of Michigan ‘24, Sports Management",
        "fun_fact": null,
        "biography": "<h5>Quick Facts</h5><ul><li>Son of Pat and Kim Brisson</li><li>Pat is a sports agent and co-head of the Hockey Division at CAA</li><li>Has one brother, Jordan.</li></ul><h5>Career Highlights</h5><ul><li>2019 World Junior A Challenge, 3rd</li></ul><h5>Olympic Experience</h5><ul><li>1-time Olympian</li><ul><li>Olympic Games Beijing 2022, 5th (Team - Men)</li></ul></ul><h5>More</h5>USA Hockey",
        "image": [
          {
            "secure_url": "https://res.cloudinary.com/usopc-prod/image/upload/v1679693702/TeamUSA%20Assets/Athlete%20Profiles/AthleteHeroDefault-1200x300.jpg"
          }
        ]
      },
      "medals": {
        "bronze": 0,
        "gold": 0,
        "silver": 0
      },
      "olympic_paralympic": "Olympian",
      "sport": [
        {
          "title": "Ice Hockey",
          "type": "Olympic",
          "season": "Winter"
        }
      ],
      "olympian_paralympian_years": "Olympian 2022",
      "olympian_paralympian_qualified": "",
      "para_classification": "",
      "hero_image": [],
      "featured_image_list": [],
      "thumbnail_image_list": [
        {
          "secure_url": "https://res.cloudinary.com/usopc-prod/image/upload/v1680009906/TeamUSA%20Assets/Athlete%20Profiles/Brendan%20Brisson%201238038/brisson_brendan_Headshot_2022_150x250.jpg"
        }
      ],
      "content_tags": [
        {
          "title": "Brendan Brisson 1238038"
        },
        {
          "title": "Beijing 2022"
        },
        {
          "title": "Ice Hockey"
        }
      ]
    },
    {
      "first_name": "Grace",
      "last_name": "Bristow",
      "bio": {
        "height": "5'5\"",
        "birthday": "2001-12-11T00:00:00",
        "hometown": {
          "city": "Murrieta",
          "state": "CA",
          "country": "United States",
          "latitude": 33.5686,
          "longitude": -117.1953
        },
        "education": "Murrieta Mesa High School (Murrieta, Calif.)  ",
        "fun_fact": null,
        "biography": "<h5>Quick Facts</h5><ul><li>Grace was born with a condition called Brachial Plexus Palsy in her right arm, which is characterized as paralysis in the arm resulting in minimal range of motion and muscle atrophy. She tried several sports while growing up, but became a swimmer when her physical therapist suggested she try swimming. Grace became involved with U.S. Paralympics Swimming in 2017</li><li>Daughter of Stefanie and Randy Bristow</li><li>Has one sister, Sarah</li><li>Hobbies include writing, reading, painting and yoga.</li></ul><h5>Career Highlights</h5><ul><li>ParaPan American Games, Lima, 2019 (400m Freestyle S10 - Women, 50m Freestyle S10 - Women, 100m Backstroke S10 - Women, 100m Freestyle S10 - Women)</li></ul>",
        "image": [
          {
            "secure_url": "https://res.cloudinary.com/usopc-prod/image/upload/v1679693702/TeamUSA%20Assets/Athlete%20Profiles/AthleteHeroDefault-1200x300.jpg"
          }
        ]
      },
      "medals": {
        "bronze": 0,
        "gold": 0,
        "silver": 0
      },
      "olympic_paralympic": "Team USA",
      "sport": [
        {
          "title": "Para Swimming",
          "type": "Paralympic",
          "season": "Summer"
        }
      ],
      "olympian_paralympian_years": "",
      "olympian_paralympian_qualified": null,
      "para_classification": "S10, SB9, SM10",
      "hero_image": [],
      "featured_image_list": [],
      "thumbnail_image_list": [
        {
          "secure_url": "https://res.cloudinary.com/usopc-prod/image/upload/v1680013448/TeamUSA%20Assets/Athlete%20Profiles/Grace%20Bristow%201149172/AthleteProfileDefaultImage.jpg"
        }
      ],
      "content_tags": [
        {
          "title": "Grace Bristow 1149172"
        }
      ]
    },
    {
      "first_name": "Brickelle",
      "last_name": "Bro",
      "bio": {
        "height": "5'9\"",
        "birthday": "1996-11-11T00:00:00",
        "hometown": {
          "city": "Castle Pines",
          "state": "CO",
          "country": "United States",
          "latitude": 39.45,
          "longitude": -104.87
        },
        "education": "Rock Canyon High School (Littleton, Colo.) ‘15 Stanford University ’15, Marine Biology",
        "fun_fact": null,
        "biography": "<h5>Quick Facts</h5><ul><li>Bro began swimming at the age of eight and had fibular hemimelia and amniotic band syndrome before birth, resulting in the amputation of both of legs below the knee. Bro made a name for herself at the 2011 CanAms and the 2012 Paralympic Trials as she went on to finish fifth at the London 2012 Paralympic Games. She set American records in the 1000y free and 1650y free as a high schooler and broke the 1650y record again as a freshman at Stanford University</li><li>Daughter of Layne and Heather Bro</li><li>Has one brother, Cayden, and one sister, Hadley</li><li>Interests include volunteering, video editing and production, playing the piano and hiking</li><li>Has 100 pairs of Converse shoes</li><li>Received a pair of high-heeled feet for her senior prom</li><li>She has set up a foundation called &#39;My Feet Don&#39;t Stink&#39;, which aims to empower young girls who have an impairment</li><li>In May 2011 she received the John Lynch Foundation Exceptional Star Of The Year Award</li><li>She was named the 2011 Colorado Disability Swimmer Of The Year.</li></ul><h5>Paralympic Experience </h5><ul><li>2-time Paralympian</li><ul><li>Paralympic Games Rio de Janeiro 2016, 7th (400m Freestyle S8 - Women), 10th (100m Freestyle S8 - Women), 13th (100m Butterfly S8 - Women), 14th (50m Freestyle S8 - Women)</li><li>Paralympic Games London 2012, 5th (400m Freestyle S8 - Women)</li></ul></ul><h5> World Championship Experience</h5><ul><li>Most recent: 2015 – 6th (200m Individual Medley SM8 - Women, 400m Freestyle S8 - Women), 7th (100m Butterfly S8 - Women, 100m Freestyle S8 - Women), 11th (50m Freestyle S8 - Women)</li><li>Years of participation: 100m Butterfly S8 - Women 2015; 100m Freestyle S8 - Women 2015; 200m Individual Medley SM8 - Women 2015; 400m Freestyle S8 - Women 2015; 50m Freestyle S8 - Women 2015</li><li>Top finish: 6th – 2015 (200m Individual Medley SM8 - Women), 2015 (400m Freestyle S8 - Women)</li></ul><h5>More</h5><p>Personal Website</p>",
        "image": [
          {
            "secure_url": "https://res.cloudinary.com/usopc-prod/image/upload/v1682699779/TeamUSA%20Assets/Migration/Athlete%20Profiles/Brickelle%20Bro%20875345/AthleteHeroDefault-1200x300.jpg"
          }
        ]
      },
      "medals": {
        "bronze": 0,
        "gold": 0,
        "silver": 0
      },
      "olympic_paralympic": "Paralympian",
      "sport": [
        {
          "title": "Para Swimming",
          "type": "Paralympic",
          "season": "Summer"
        }
      ],
      "olympian_paralympian_years": "Paralympian 2012, 2016",
      "olympian_paralympian_qualified": null,
      "para_classification": "S8, SB7, SM8",
      "hero_image": [],
      "featured_image_list": [],
      "thumbnail_image_list": [
        {
          "secure_url": "https://res.cloudinary.com/usopc-prod/image/upload/v1682699781/TeamUSA%20Assets/Migration/Athlete%20Profiles/Brickelle%20Bro%20875345/Bro_Brickelle_2016_Headshot_150x250.jpg"
        }
      ],
      "content_tags": [
        {
          "title": "Brickelle Bro 875345"
        }
      ]
    },
    {
      "first_name": "Allison",
      "last_name": "Brock",
      "bio": {
        "height": "5'6\"",
        "birthday": "1979-12-07T00:00:00",
        "hometown": {
          "city": "Wellington",
          "state": "FL",
          "country": "United States",
          "latitude": 26.6567,
          "longitude": -80.2667
        },
        "education": "Kailua High School (Kailua, Hawaii) ‘97",
        "fun_fact": null,
        "biography": "<h5>Quick Facts</h5><ul><li>Daughter of James Brock and Leslie Galloway</li><li>Began riding at age 7</li><li>At age 17, left Hawaii to pursue a career in equestrian.</li></ul><h5>Career Highlights</h5><ul>\r\n                            <li>2016 CDIO5* Nations Cup at Compiegne, 1st (team) – with Rosevelt</li>\r\n                            <li>2016 CDI4* Adequan Global Dressage Festival 10 Grand Prix, 1st (individual) – with Rosevelt</li>\r\n                            <li>2016 CDI4* Adequan Global Dressage Festival 10 Grand Prix Special, 2nd (individual) – with Rosevelt</li>\r\n                            <li>2015 CDIO5* Nations Cup at Compiegne, 1st (team) – with Rosevelt</li>\r\n                            <li>2015 CDI4* Achleiten Schloss, 2nd (individual) – with Rosevelt </li>\r\n                    </ul><h5>Olympic Experience </h5><ul><li>1-time Olympian; 1-time Olympic medalist (1 bronze)</li><ul><li>Olympic Games Rio de Janeiro 2016, bronze (Team - Open), 15th (Individual - Open)</li></ul></ul><h5>More</h5>Personal Website<br>\nU.S. Equestrian Federation",
        "image": [
          {
            "secure_url": "https://res.cloudinary.com/usopc-prod/image/upload/v1686915901/TeamUSA%20Assets/Migration/Athlete%20Profiles/Allison%20Brock/Brock_Allison_081016_1200x300.jpg"
          }
        ]
      },
      "medals": {
        "bronze": 1,
        "gold": 0,
        "silver": 0
      },
      "olympic_paralympic": "Olympian",
      "sport": [
        {
          "title": "Equestrian",
          "type": "Olympic",
          "season": "Summer"
        }
      ],
      "olympian_paralympian_years": "Olympian 2016",
      "olympian_paralympian_qualified": null,
      "para_classification": null,
      "hero_image": [],
      "featured_image_list": [],
      "thumbnail_image_list": [
        {
          "secure_url": "https://res.cloudinary.com/usopc-prod/image/upload/v1686915904/TeamUSA%20Assets/Migration/Athlete%20Profiles/Allison%20Brock/brock_allison_150x250.jpg"
        }
      ],
      "content_tags": [
        {
          "title": "Allison Brock"
        }
      ]
    },
    {
      "first_name": "Malcolm",
      "last_name": "Brogdon",
      "bio": {
        "height": "6'5\"",
        "birthday": "1992-12-11T00:00:00",
        "hometown": {
          "city": "Atlanta",
          "state": "GA",
          "country": "United States",
          "latitude": 33.7488,
          "longitude": -84.3877
        },
        "education": "University of Virginia",
        "fun_fact": "",
        "biography": "<strong></strong><table align=\"right\"><tbody><tr><td><strong ><br bold=\"[object Object]\"/></strong></td><td><strong ><br bold=\"[object Object]\"/></strong></td><td style=\"text-align: justify;\"><strong ><br bold=\"[object Object]\"/></strong></td></tr></tbody></table><strong></strong><strong>Name</strong>: Malcolm Brogdon<br /><strong>Current Team</strong>: University of Virginia<br /><strong>Position</strong>: Guard<br /><strong>Height</strong>: 6-5<br /><strong>Hometown</strong>: Atlanta, Ga.<br /><strong>High School</strong>: Greater Atlanta Christian School (Norcross, Ga.) ‘11<br /><strong>College</strong>: University of Virginia ’15, History<div><br /><div><p>&nbsp;</p><h5>Career Highlights</h5><ul><li>Pan American Games, Toronto, 2015 (Team - Men)</li></ul><h5>Quick Facts</h5><ul><li>Son of Jann Adams and Mitchell G. Brogdon</li><li>Has two siblings; Gino and John</li><li>2011 Mr. Basketball Georgia.</li></ul><br /><br /><p>&nbsp;</p><h5>More</h5><p>USA Basketball</p><p>&nbsp;</p></div></div>",
        "image": [
          {
            "secure_url": "https://res.cloudinary.com/usopc-prod/image/upload/v1682699857/TeamUSA%20Assets/Migration/Athlete%20Profiles/Malcolm%20Brogdon%201192992/AthleteHeroDefault-1200x300.jpg"
          }
        ]
      },
      "medals": {
        "bronze": 0,
        "gold": 0,
        "silver": 0
      },
      "olympic_paralympic": "Team USA",
      "sport": [
        {
          "title": "Basketball",
          "type": "Olympic",
          "season": "Summer"
        }
      ],
      "olympian_paralympian_years": "",
      "olympian_paralympian_qualified": "",
      "para_classification": "",
      "hero_image": [],
      "featured_image_list": [],
      "thumbnail_image_list": [
        {
          "secure_url": "https://res.cloudinary.com/usopc-prod/image/upload/v1682699858/TeamUSA%20Assets/Migration/Athlete%20Profiles/Malcolm%20Brogdon%201192992/Basketball_Men_Brogdon_Malcolm.jpg"
        }
      ],
      "content_tags": [
        {
          "title": "Malcolm Brogdon 1192992"
        },
        {
          "title": "Alumni Class of 2025"
        }
      ]
    },
    {
      "first_name": "Murphy",
      "last_name": "Bromberg",
      "bio": {
        "height": "5'2\"",
        "birthday": "1995-07-12T00:00:00",
        "hometown": {
          "city": "Bexley",
          "state": "OH",
          "country": "United States",
          "latitude": 39.967,
          "longitude": -82.9307
        },
        "education": "University of Texas",
        "fun_fact": "",
        "biography": "<h5>Quick Facts</h5><ul><li>Murphy is the daughter of Danny and Karen Bromberg</li><li>She has an older sister, Jennie, and a younger brother, David</li><li>She began diving at age nine and now trains three to four hours a day, five days a week</li><li>She says the most difficult part of training is trying to balance diving with school and her social life</li><li>When she's not diving, Murphy enjoys reading, hiking, and painting by numbers</li><li>Earned a degree in corporate communications from the University of Texas and is now working on a masters in sport management</li><li><p>Bexley High School (‘13) University of Texas</p></li></ul><h5>Career Highlights</h5><ul><li>World Cup Final, Wuhan, 2018 (3m Springboard Synchro - Women)</li><li>World Cup, Rio de Janeiro, 2016 (10m Platform - Women)</li><li>Pan American Games, Toronto, 2015 (10m Platform Synchro - Women, 10m Platform - Women)</li><li>World Cup, Shanghai, 2014 (10m Platform - Women)</li></ul><h5>World Championships Experience</h5><ul><li>Most recent: 2019 – bronze (10m Platform Synchro - Women)</li><li>Years of participation: 10m Platform Synchro - Women 2013, 2019; 10m Platform Synchro - Mixed 2015</li><li>Medals: 1 (1 bronze)</li><ul><li>Bronze – 2019 (10m Platform Synchro - Women)</li></ul></ul>",
        "image": [
          {
            "secure_url": "https://res.cloudinary.com/usopc-prod/image/upload/v1682699884/TeamUSA%20Assets/Migration/Athlete%20Profiles/Murphy%20Bromberg%20814855/AthleteHeroDefault-1200x300.jpg"
          }
        ]
      },
      "medals": {
        "bronze": 0,
        "gold": 0,
        "silver": 0
      },
      "olympic_paralympic": "Team USA",
      "sport": [
        {
          "title": "Diving",
          "type": "Olympic",
          "season": "Summer"
        }
      ],
      "olympian_paralympian_years": "",
      "olympian_paralympian_qualified": "",
      "para_classification": "",
      "hero_image": [],
      "featured_image_list": [],
      "thumbnail_image_list": [
        {
          "secure_url": "https://res.cloudinary.com/usopc-prod/image/upload/v1682699886/TeamUSA%20Assets/Migration/Athlete%20Profiles/Murphy%20Bromberg%20814855/Murphy-Bromberg-150x250.jpg"
        }
      ],
      "content_tags": [
        {
          "title": "Murphy Bromberg 814855"
        },
        {
          "title": "Alumni Class of 2025"
        }
      ]
    },
    {
      "first_name": "Trayvon",
      "last_name": "Bromell",
      "bio": {
        "height": "5'8\"",
        "birthday": "1995-07-10T00:00:00",
        "hometown": {
          "city": "St. Petersburg",
          "state": "FL",
          "country": "United States",
          "latitude": 27.7676,
          "longitude": -82.6403
        },
        "education": "Baylor University",
        "fun_fact": null,
        "biography": "<h5>Quick Facts</h5><ul><li>Son of Cashmere Bromell and Shri Sanders</li><li>Has two brothers and one sister</li><li>Father, Cashmere, played in the Canadian Football League</li><li>Won the gold medal at the 2016 IAAF World Indoor Championships in the 60-meter when he was 20 years old</li><li>First high school athlete to ever finish under the 10-second mark in the 100-meter</li><li>Claimed two NCAA titles (100, 200) while at Baylor University</li><li>Passionate about photography.</li></ul><p></p><p>Years of <span>World Championships </span>participation: Outdoor – 2015 (100-meter); Indoor – 2016 (60-meter). <span>Most recent: 2016 – gold (60-meter). </span>Medals: 2 (1 gold, 1 bronze).</p><h5>More</h5><p>USA Track &amp; Field</p><h5>Olympic Experience</h5><ul><li>2-time Olympian</li><ul><li>Olympic Games Tokyo 2020, 8th (4 x 100m Relay - Men), 10th (100m - Men)</li><li>Olympic Games Rio de Janeiro 2016, 7th (4 x 100m Relay - Men), 8th (100m - Men)</li></ul></ul><h5>World Championships Experience</h5><ul><li>Most recent: 2016 – gold (60m (Indoor) - Men)</li><li>Years of participation: 60m (Indoor) - Men 2016; 100m - Men 2015; 4 x 100m Relay - Men 2015</li><li>Medals: 2 (1 gold, 1 bronze)</li><ul><li>Gold – 2016 (60m (Indoor) - Men)</li><li>Bronze – 2015 (100m - Men)</li></ul></ul>",
        "image": [
          {
            "secure_url": "https://res.cloudinary.com/usopc-prod/image/upload/v1687662544/TeamUSA%20Assets/Athlete%20Profiles/Trayvon%20Bromell%20933908/Bromell_T_Bio_933908.png"
          }
        ]
      },
      "medals": {
        "bronze": 0,
        "gold": 0,
        "silver": 0
      },
      "olympic_paralympic": "Olympian",
      "sport": [
        {
          "title": "Track and Field",
          "type": "Olympic",
          "season": "Summer"
        }
      ],
      "olympian_paralympian_years": "Olympian 2016, 2020",
      "olympian_paralympian_qualified": "",
      "para_classification": "",
      "hero_image": [
        {
          "secure_url": "https://res.cloudinary.com/usopc-prod/image/upload/v1687662147/TeamUSA%20Assets/Athlete%20Profiles/batch%20images/Bromell_T_Hero_933908.png"
        }
      ],
      "featured_image_list": [],
      "thumbnail_image_list": [
        {
          "secure_url": "https://res.cloudinary.com/usopc-prod/image/upload/v1680013393/TeamUSA%20Assets/Athlete%20Profiles/Trayvon%20Bromell%20933908/Bromell_Trayvon_150x250.jpg"
        }
      ],
      "content_tags": [
        {
          "title": "Trayvon Bromell 933908"
        }
      ]
    },
    {
      "first_name": "Chris",
      "last_name": "Brooks",
      "bio": {
        "height": "5'8\"",
        "birthday": "1986-12-19T00:00:00",
        "hometown": {
          "city": "Houston",
          "state": "TX",
          "country": "United States",
          "latitude": 29.7604,
          "longitude": -95.3698
        },
        "education": "Cypress Creek High School (Houston, Texas) ‘05 University of Oklahoma ‘09, Business Management",
        "fun_fact": null,
        "biography": "<h5>Quick Facts</h5><ul><li>Son of Terry and the late Larry Brooks</li><li>Has one brother, Nick, and one sister, Erica</li><li>Competed in gymnastics for the University of Oklahoma, where he helped lead the Sooners to the 2008 NCAA title</li><li>Interests include cars and motorcycles</li><li>Began gymnastics in 1991</li><li>Favorite event is horizontal bar.</li></ul><h5>Olympic Experience </h5><ul><li>1-time Olympian</li><ul><li>Olympic Games Rio de Janeiro 2016, 5th (Team - Men), 14th (Individual All-Around - Men), 16th (Parallel Bars - Men), 20th (Horizontal Bar - Men), 23th (Rings - Men), 28th (Floor Exercise - Men), 65th (Pommel Horse - Men)</li></ul></ul><h5> World Championship Experience</h5><ul><li>Most recent: 2015 – 5th (Team - Men), 6th (Horizontal Bar - Men), 41th (Rings - Men), 43th (Individual All-Around - Men), 45th (Floor Exercise - Men), 176th (Pommel Horse - Men), 187th (Parallel Bars - Men)</li><li>Years of participation: Floor Exercise - Men 2010, 2015; Horizontal Bar - Men 2010, 2015; Individual All-Around - Men 2010, 2015; Parallel Bars - Men 2010, 2015; Pommel Horse - Men 2010, 2015; Rings - Men 2015; Team - Men 2010, 2015</li><li>Top finish: 4th – 2010 (Team - Men)</li></ul><h5>More</h5>USA Gymnastics",
        "image": [
          {
            "secure_url": "https://res.cloudinary.com/usopc-prod/image/upload/v1686320778/TeamUSA%20Assets/Migration/Athlete%20Profiles/AthleteHeroDefault-1200x300.jpg"
          }
        ]
      },
      "medals": {
        "bronze": 0,
        "gold": 0,
        "silver": 0
      },
      "olympic_paralympic": "Olympian",
      "sport": [
        {
          "title": "Gymnastics",
          "type": "Olympic",
          "season": "Summer"
        }
      ],
      "olympian_paralympian_years": "Olympian 2016",
      "olympian_paralympian_qualified": null,
      "para_classification": null,
      "hero_image": [],
      "featured_image_list": [],
      "thumbnail_image_list": [
        {
          "secure_url": "https://res.cloudinary.com/usopc-prod/image/upload/v1686916552/TeamUSA%20Assets/Migration/Athlete%20Profiles/Chris%20Brooks/Brooks_Chris_150x250.jpg"
        }
      ],
      "content_tags": [
        {
          "title": "Chris Brooks"
        }
      ]
    }
  ]
}